LICENSE.txt
README.md
beancount_n26_with_regexes/__init__.py
beancount_n26_with_regexes-0.6.0.dist-info/LICENSE.txt
beancount_n26_with_regexes-0.6.0.dist-info/WHEEL
beancount_n26_with_regexes-0.6.0.dist-info/METADATA
beancount_n26_with_regexes-0.6.0.dist-info/RECORD
