Metadata-Version: 2.1
Name: beancount-n26-with-regexes
Version: 0.6.0
Summary: Beancount Importer for N26 CSV exports with extended regex classification
Home-page: https://github.com/Eazhi/beancount-n26-with-regexes
License: MIT
Keywords: banking,beancount,cli-accounting,finance
Author: KHUAT DUY Paul
Requires-Python: >=3.6.2,<4.0.0
Classifier: Development Status :: 4 - Beta
Classifier: Environment :: Plugins
Classifier: Intended Audience :: End Users/Desktop
Classifier: Intended Audience :: Financial and Insurance Industry
Classifier: License :: OSI Approved :: MIT License
Classifier: Programming Language :: Python :: 3
Classifier: Programming Language :: Python :: 3 :: Only
Classifier: Programming Language :: Python :: 3.10
Classifier: Programming Language :: Python :: 3.6
Classifier: Programming Language :: Python :: 3.7
Classifier: Programming Language :: Python :: 3.8
Classifier: Programming Language :: Python :: 3.9
Classifier: Topic :: Office/Business :: Financial
Classifier: Topic :: Office/Business :: Financial :: Accounting
Requires-Dist: beancount (>=2.2,<3.0)
Project-URL: Repository, https://github.com/Eazhi/beancount-n26-with-regexes
